LICENSE.md
MANIFEST.in
README.md
setup.py
socketlabs/__init__.py
socketlabs/constants.py
socketlabs/exceptions.py
socketlabs/socketlabs.py
socketlabs.egg-info/PKG-INFO
socketlabs.egg-info/SOURCES.txt
socketlabs.egg-info/dependency_links.txt
socketlabs.egg-info/requires.txt
socketlabs.egg-info/top_level.txt