Metadata-Version: 1.1
Name: socketlabs
Version: 0.1.1
Summary: A Python interface to the SocketLabs API.
Home-page: https://github.com/MattHealy/socketlabs-python
Author: Matt Healy
Author-email: healmatt@gmail.com
License: MIT
Keywords: socketlabs email
Platform: UNKNOWN
Classifier: Development Status :: 1 - Planning
Classifier: Intended Audience :: Developers
Classifier: Topic :: Communications :: Email
Classifier: License :: OSI Approved :: MIT License
Classifier: Programming Language :: Python :: 3.5
